README.md
setup.py
xtable/__init__.py
xtable/__main__.py
xtable/tblfmt.py
xtable.egg-info/PKG-INFO
xtable.egg-info/SOURCES.txt
xtable.egg-info/dependency_links.txt
xtable.egg-info/entry_points.txt
xtable.egg-info/requires.txt
xtable.egg-info/top_level.txt