Metadata-Version: 2.1
Name: xtable
Version: 1.0.7
Summary: print table in console
Home-page: https://github.com/walkerever/xtable
Author: Yonghang Wang
Author-email: wyhang@gmail.com
License: Apache 2
Keywords: xtable,table,simpletable,quicktable
Platform: UNKNOWN
Classifier: License :: OSI Approved :: Apache Software License
